happyxpy/__init__.py
happyxpy/constants.py
happyxpy/happyx_unix_amd64.so
happyxpy/happyx_unix_arm64.so
happyxpy/happyx_win.pyd
happyxpy/server.py
happyxpy-4.4.1.dist-info/METADATA
happyxpy-4.4.1.dist-info/WHEEL
happyxpy-4.4.1.dist-info/top_level.txt
happyxpy-4.4.1.dist-info/RECORD
